slackblockstool/__init__.py
slackblockstool/blocks.py
slackblockstool/event.py
slackblockstool/parser.py
slackblockstool/view.py
slackblockstool-0.2.6.dist-info/LICENSE
slackblockstool-0.2.6.dist-info/METADATA
slackblockstool-0.2.6.dist-info/WHEEL
slackblockstool-0.2.6.dist-info/top_level.txt
slackblockstool-0.2.6.dist-info/RECORD
