Metadata-Version: 2.1
Name: slackblockstool
Version: 0.2.6
Summary: Tool for Slack Blocks
Home-page: 
Author: shinsuke masuda
Author-email: shinsuke.masuda@gmail.com
License: UNKNOWN
Platform: UNKNOWN
Classifier: Programming Language :: Python :: 3
Classifier: License :: OSI Approved :: MIT License
Classifier: Operating System :: OS Independent
Requires-Python: >=3.6
License-File: LICENSE
Requires-Dist: slack-sdk
